org_todo_metrics/__init__.py
org_todo_metrics/cli.py
org_todo_metrics/datastructures.py
org_todo_metrics/org_todo_metrics.py
org_todo_metrics-0.1.3.dist-info/AUTHORS.rst
org_todo_metrics-0.1.3.dist-info/LICENSE
org_todo_metrics-0.1.3.dist-info/METADATA
org_todo_metrics-0.1.3.dist-info/WHEEL
org_todo_metrics-0.1.3.dist-info/entry_points.txt
org_todo_metrics-0.1.3.dist-info/top_level.txt
org_todo_metrics-0.1.3.dist-info/RECORD
