Metadata-Version: 2.1
Name: org-todo-metrics
Version: 0.1.3
Summary: given some org files, compute and display interesting and useful metrics
Home-page: https://gitlab.com/reedrichards/org_todo_metrics
Author: Robert Wendt
Author-email: rwendt1337@gmail.com
License: MIT license
Keywords: org_todo_metrics
Platform: UNKNOWN
Classifier: Development Status :: 2 - Pre-Alpha
Classifier: Intended Audience :: Developers
Classifier: License :: OSI Approved :: MIT License
Classifier: Natural Language :: English
Classifier: Programming Language :: Python :: 3
Classifier: Programming Language :: Python :: 3.6
Classifier: Programming Language :: Python :: 3.7
Classifier: Programming Language :: Python :: 3.8
Requires-Python: >=3.6
Requires-Dist: Click (>=7.0)
Requires-Dist: orgparse
Requires-Dist: starlette
